flask_seeder/__init__.py
flask_seeder/cli.py
flask_seeder/faker.py
flask_seeder/generator.py
flask_seeder/parser.py
flask_seeder/seeder.py
flask_seeder/data/domains/domains.txt
flask_seeder/data/names/names.txt
tests/__init__.py
tests/test_cli.py
tests/test_faker.py
tests/test_flask_seeder.py
tests/test_seeder.py
tests/generator/__init__.py
tests/generator/test_email.py
tests/generator/test_generator.py
tests/generator/test_integer.py
tests/generator/test_name.py
tests/generator/test_sequence.py
tests/generator/test_string.py
tests/generator/test_uuid.py
tests/parser/__init__.py
tests/parser/test_parser.py
tests/parser/test_tokenizer.py
Flask_Seeder-1.2.0.dist-info/METADATA
Flask_Seeder-1.2.0.dist-info/WHEEL
Flask_Seeder-1.2.0.dist-info/entry_points.txt
Flask_Seeder-1.2.0.dist-info/top_level.txt
Flask_Seeder-1.2.0.dist-info/RECORD
