Metadata-Version: 2.1
Name: Flask-Seeder
Version: 1.2.0
Summary: Flask extension to seed database through scripts
Home-page: https://github.com/diddi-/flask-seeder
Author: Diddi Oskarsson
Author-email: diddi@diddi.se
License: MIT
Platform: UNKNOWN
Classifier: Programming Language :: Python :: 3
Classifier: License :: OSI Approved :: MIT License
Classifier: Operating System :: OS Independent
